funiculi/__init__.py
funiculi/__main__.py
funiculi/api.py
funiculi/cli.py
funiculi/errors.py
funiculi/fire_workarounds.py
funiculi/logging.py
funiculi/settings.py
funiculi/version.py
funiculi-0.2.0.dist-info/LICENSE
funiculi-0.2.0.dist-info/METADATA
funiculi-0.2.0.dist-info/WHEEL
funiculi-0.2.0.dist-info/entry_points.txt
funiculi-0.2.0.dist-info/RECORD
