Metadata-Version: 2.1
Name: funiculi
Version: 0.2.0
Summary: Control your Denon AVR amplifier from the command line
License: Apache-2.0
Author: Claudia Pellegrino
Author-email: clau@tiqua.de
Requires-Python: >=3.8
Classifier: Development Status :: 3 - Alpha
Classifier: License :: OSI Approved :: Apache Software License
Classifier: Operating System :: MacOS
Classifier: Operating System :: POSIX :: Linux
Classifier: Programming Language :: Python :: 3
Classifier: Programming Language :: Python :: 3.8
Classifier: Programming Language :: Python :: 3.9
Classifier: Programming Language :: Python :: 3.10
Classifier: Programming Language :: Python :: 3.11
Classifier: Programming Language :: Python :: 3.12
Classifier: Topic :: Home Automation
Classifier: Topic :: Utilities
Requires-Dist: colorama
Requires-Dist: fire
